LICENSE
README.md
setup.py
split_openfeature_provider/__init__.py
split_openfeature_provider/split_client_wrapper.py
split_openfeature_provider/split_provider.py
split_openfeature_provider.egg-info/PKG-INFO
split_openfeature_provider.egg-info/SOURCES.txt
split_openfeature_provider.egg-info/dependency_links.txt
split_openfeature_provider.egg-info/top_level.txt