Metadata-Version: 2.1
Name: split-openfeature-provider
Version: 1.0.0
Summary: The official Python Split Provider for OpenFeature
License: Apache License 2.0
Classifier: Programming Language :: Python :: 3
Classifier: Topic :: Software Development :: Libraries
Requires-Python: >=3.9
License-File: LICENSE
